distcode_ex/Binomialdistribution.py
distcode_ex/Gaussiandistribution.py
distcode_ex/Generaldistribution.py
distcode_ex/__init__.py
distcode_ex-1.0.dist-info/METADATA
distcode_ex-1.0.dist-info/WHEEL
distcode_ex-1.0.dist-info/top_level.txt
distcode_ex-1.0.dist-info/RECORD
