Metadata-Version: 2.1
Name: distcode_ex
Version: 1.0
Summary: Gaussian distributions
Author: Opeyemi Oladipupo
Author-email: techrystein@gmail.com
